pytorch_fid/__init__.py
pytorch_fid/__main__.py
pytorch_fid/fid_score.py
pytorch_fid/inception.py
pytorch_fid-0.3.0.dist-info/LICENSE
pytorch_fid-0.3.0.dist-info/METADATA
pytorch_fid-0.3.0.dist-info/WHEEL
pytorch_fid-0.3.0.dist-info/entry_points.txt
pytorch_fid-0.3.0.dist-info/top_level.txt
pytorch_fid-0.3.0.dist-info/RECORD
