Metadata-Version: 2.1
Name: pytorch-fid
Version: 0.3.0
Summary: Package for calculating Frechet Inception Distance (FID) using PyTorch
Home-page: https://github.com/mseitzer/pytorch-fid
Author: Max Seitzer
Classifier: Programming Language :: Python :: 3
Classifier: License :: OSI Approved :: Apache Software License
Requires-Python: >=3.5
Provides-Extra: dev
License-File: LICENSE
